<?xml version="1.0" encoding="UTF-8"?>
<site>
   <description url="http://caltrop.sourceforge.net/eclipse">
      Eclipse download site for CAL
   </description>
   <feature url="features/net.sf.caltrop.eclipse.plugin.calfeature_1.0.3.jar" id="net.sf.caltrop.eclipse.plugin.calfeature" version="1.0.3">
      <category name="caltrop"/>
   </feature>
   <feature url="features/net.sf.caltrop.eclipse.plugin.calfeature_1.0.4.jar" id="net.sf.caltrop.eclipse.plugin.calfeature" version="1.0.4">
      <category name="caltrop"/>
   </feature>
   <feature url="features/net.sf.caltrop.eclipse.plugin.calfeature_1.0.5.jar" id="net.sf.caltrop.eclipse.plugin.calfeature" version="1.0.5">
      <category name="caltrop"/>
   </feature>
   <feature url="features/net.sf.caltrop.eclipse.plugin.calfeature_1.0.6.jar" id="net.sf.caltrop.eclipse.plugin.calfeature" version="1.0.6">
      <category name="caltrop"/>
   </feature>
   <category-def name="caltrop" label="CAL Editor Plug-in">
      <description>
         An editor for both CAL and NL that provides coloring and on-the-fly syntax, semantic checking of the document.
      </description>
   </category-def>
</site>
