<?xml version="1.0" encoding="UTF-8"?>
<feature
      id="net.sf.opendf.eclipse.feature"
      label="Open Dataflow Plugin"
      version="1.2.12"
      provider-name="The Open Dataflow Project">

   <description>
      Open Dataflow Project plugin
V1.2.5
* improved simulation speed
* Action priority analysis bug fixed
* NL parsing bug fixed (type parameters)
V1.2.4
* Reverted to Java 1.5
V1.2.3
===============================================
* Improved console I/O behavior
* Minor bug fixes
V1.2.0
===============================================
* Improved simulator interface
* Run config dialog tab for console I/O control
* Improved error reporting from editor
V1.1.0
===============================================
* make dataflow simulator available from the std Eclipse run
dialog.
* fix problems opening files outside project
V1.0.1
===============================================
* Improved outlining including icons and preservation of expanded
state.
* Changed .CAL and .NL images.
* Added to PDF documentation.
   </description>

   <copyright>
      Copyright (c) 2008, Xilinx Inc.
All rights reserved.
   </copyright>

   <license>
      Copyright (c) 2008, Xilinx Inc.
All rights reserved.
Redistribution and use in source and binary forms, with or without
modification, are permitted provided that the following conditions
are met:
- Redistributions of source code must retain the above copyright
notice, this list of conditions and the following disclaimer.
- Redistributions in binary form must reproduce the above copyright
notice, this list of conditions and the following disclaimer
in the documentation and/or other materials provided with the
distribution.
- Neither the name of Xilinx Inc. nor the names of its contributors
may be used to endorse or promote products derived from this
software without specific prior written permission.
THIS SOFTWARE IS PROVIDED BY THE COPYRIGHT HOLDERS AND CONTRIBUTORS
&quot;AS IS&quot; AND ANY EXPRESS OR IMPLIED WARRANTIES, INCLUDING, BUT
NOT LIMITED TO, THE IMPLIED WARRANTIES OF MERCHANTABILITY AND
FITNESS FOR A PARTICULAR PURPOSE ARE DISCLAIMED. IN NO EVENT
SHALL THE COPYRIGHT OWNER OR CONTRIBUTORS BE LIABLE FOR ANY DIRECT,
INDIRECT, INCIDENTAL,SPECIAL, EXEMPLARY, OR CONSEQUENTIAL DAMAGES
(INCLUDING, BUT NOT LIMITED TO, PROCUREMENT OF SUBSTITUTE GOODS
OR SERVICES;LOSS OF USE, DATA, OR PROFITS; OR BUSINESS INTERRUPTION)
HOWEVER CAUSED AND ON ANY THEORY OF LIABILITY, WHETHER IN CONTRACT,
STRICT LIABILITY, OR TORT (INCLUDING NEGLIGENCE OR OTHERWISE)
ARISING IN ANY WAY OUT OF THE USE OF THIS SOFTWARE, EVEN IF ADVISED
OF THE POSSIBILITY OF SUCH DAMAGE.
   </license>

   <url>
      <update label="Open Dataflow Project Update Site" url="http://opendf.sourceforge.net/eclipse"/>
      <discovery label="Open Dataflow Project" url="http://opendf.sourceforge.net/eclipse"/>
   </url>

   <requires>
      <import plugin="org.eclipse.core.runtime"/>
      <import plugin="org.eclipse.debug.ui"/>
      <import plugin="org.eclipse.jface.text"/>
      <import plugin="org.eclipse.ui"/>
      <import plugin="org.eclipse.ui.console"/>
      <import plugin="org.eclipse.ui.editors"/>
      <import plugin="org.eclipse.ui.ide"/>
      <import plugin="org.eclipse.ui.views"/>
      <import plugin="org.eclipse.ui.workbench.texteditor"/>
   </requires>

   <plugin
         id="net.sf.opendf.eclipse.core"
         download-size="0"
         install-size="0"
         version="1.1.10"
         unpack="false"/>

   <plugin
         id="net.sf.opendf.eclipse.doc"
         download-size="0"
         install-size="0"
         version="1.0.1"/>

   <plugin
         id="net.sf.opendf.eclipse.plugin"
         download-size="0"
         install-size="0"
         version="1.2.10"
         unpack="false"/>

</feature>
